spotify_to_sqlite/__init__.py
spotify_to_sqlite/__main__.py
spotify_to_sqlite/cli.py
spotify_to_sqlite/constants.py
spotify_to_sqlite/utils.py
spotify_to_sqlite-0.2.1.dist-info/LICENSE
spotify_to_sqlite-0.2.1.dist-info/METADATA
spotify_to_sqlite-0.2.1.dist-info/WHEEL
spotify_to_sqlite-0.2.1.dist-info/entry_points.txt
spotify_to_sqlite-0.2.1.dist-info/top_level.txt
spotify_to_sqlite-0.2.1.dist-info/RECORD
