Metadata-Version: 2.1
Name: spotify-to-sqlite
Version: 0.2.1
Summary: Convert a Spotify export zip to a SQLite database
Home-page: https://github.com/chekos/spotify-to-sqlite
Author: Sergio Sanchez
License: Apache License, Version 2.0
Project-URL: Issues, https://github.com/chekos/spotify-to-sqlite/issues
Project-URL: CI, https://github.com/chekos/spotify-to-sqlite/actions
Project-URL: Changelog, https://github.com/chekos/spotify-to-sqlite/releases
Requires-Python: >=3.6
License-File: LICENSE
Requires-Dist: typer (==0.6.1)
Requires-Dist: sqlite-utils (==3.30)
Requires-Dist: spotipy (==2.19)
Requires-Dist: python-dotenv (==0.19.2)
Requires-Dist: rich (==12.6.0)
Provides-Extra: dev
Requires-Dist: black (>=22.1.0) ; extra == 'dev'
Requires-Dist: datasette (>=0.60.2) ; extra == 'dev'
Requires-Dist: ipykernel (>=6.9.1) ; extra == 'dev'
Requires-Dist: isort (>=5.10.1) ; extra == 'dev'
Requires-Dist: pytest (>=7.0.1) ; extra == 'dev'
Requires-Dist: pytest-dotenv (>=0.5.2) ; extra == 'dev'
Requires-Dist: ipywidgets (==7.6.5) ; extra == 'dev'
Provides-Extra: jupyter
Requires-Dist: ipywidgets (==7.6.5) ; extra == 'jupyter'
Provides-Extra: test
Requires-Dist: pytest (>=7.0.1) ; extra == 'test'
Requires-Dist: pytest-dotenv (>=0.5.2) ; extra == 'test'
